libapt/__init__.py
libapt/apt.py
libapt/cache.py
libapt/deb.py
libapt/download.py
libapt/generator.py
libapt/pool.py
libapt/py.typed
libapt/release.py
libapt/signature.py
libapt/stanza.py
libapt/version.py
libapt-1.0.1.dist-info/METADATA
libapt-1.0.1.dist-info/WHEEL
libapt-1.0.1.dist-info/licenses/LICENSE
libapt-1.0.1.dist-info/RECORD
