Metadata-Version: 2.4
Name: libapt
Version: 1.0.1
Summary: Interface with Debian APT package repositories.
Project-URL: Homepage, https://github.com/eLiSCHe/libapt
Author-email: Thomas Irgang <thomas@irgang.eu>
License-File: LICENSE
Classifier: Development Status :: 3 - Alpha
Classifier: License :: OSI Approved :: GNU General Public License v3 (GPLv3)
Classifier: Programming Language :: Python :: 3
Requires-Python: >=3.11
Requires-Dist: libyamlconf>=1.2.1
Requires-Dist: pgpy>=0.6.0
Requires-Dist: pydantic>=2.10.6
Requires-Dist: python-dateutil>=2.9.0.post0
Requires-Dist: python-gnupg>=0.5.4
Requires-Dist: requests>=2.32.3
Requires-Dist: standard-imghdr>=3.13.0
Requires-Dist: unix-ar>=0.2.1
Requires-Dist: zstandard>=0.23.0
